hera_strip-1.0.1.dist-info/licenses/LICENSE
herastrip/__init__.py
herastrip/__main__.py
herastrip/beam.py
herastrip/main.py
herastrip/plotting.py
herastrip/simulation.py
herastrip/sky_model.py
hera_strip-1.0.1.dist-info/METADATA
hera_strip-1.0.1.dist-info/WHEEL
hera_strip-1.0.1.dist-info/entry_points.txt
hera_strip-1.0.1.dist-info/top_level.txt
hera_strip-1.0.1.dist-info/RECORD
