Metadata-Version: 2.4
Name: hera_strip
Version: 1.0.1
Summary: HERA strip: A tool for simulating and visualizing diffuse sky models for HERA observations.
Author-email: Kartik Mandar <kartik4321mandar@gmail.com>
License: MIT
Project-URL: Homepage, https://github.com/RRI-interferometry/hera_strip
Project-URL: Repository, https://github.com/RRI-interferometry/hera_strip.git
Project-URL: Issues, https://github.com/RRI-interferometry/hera_strip/issues
Classifier: Programming Language :: Python :: 3
Classifier: Programming Language :: Python :: 3.10
Classifier: Programming Language :: Python :: 3.11
Classifier: Programming Language :: Python :: 3.12
Classifier: License :: OSI Approved :: MIT License
Classifier: Operating System :: OS Independent
Classifier: Intended Audience :: Science/Research
Classifier: Topic :: Scientific/Engineering :: Astronomy
Requires-Python: >=3.10
License-File: LICENSE
Requires-Dist: numpy
Requires-Dist: astropy
Requires-Dist: healpy
Requires-Dist: pygdsm
Requires-Dist: bokeh
Requires-Dist: matplotlib
Requires-Dist: scipy
Requires-Dist: pyradiosky
Requires-Dist: pyuvdata
Dynamic: license-file
